tell_py/__init__.py
tell_py/sender.py
tell_py/tell.py
tell_py-0.1.1.dist-info/METADATA
tell_py-0.1.1.dist-info/WHEEL
tell_py-0.1.1.dist-info/top_level.txt
tell_py-0.1.1.dist-info/RECORD
