Metadata-Version: 2.4
Name: tell-py
Version: 0.1.1
Summary: Telegram logging utility for Python
Author-email: Rompni <andresnavarrodev@gmail.com>
License: MIT
Requires-Python: >=3.7
Requires-Dist: requests
Requires-Dist: python-dotenv
